webcrystal.py
webcrystal-1.0.1.data/scripts/webcrystal.py
webcrystal-1.0.1.dist-info/DESCRIPTION.rst
webcrystal-1.0.1.dist-info/METADATA
webcrystal-1.0.1.dist-info/RECORD
webcrystal-1.0.1.dist-info/WHEEL
webcrystal-1.0.1.dist-info/metadata.json
webcrystal-1.0.1.dist-info/top_level.txt
