Metadata-Version: 2.0
Name: webcrystal
Version: 1.0.1
Summary: A website archival tool and format.
Home-page: http://dafoster.net/projects/webcrystal/
Author: David Foster
Author-email: david@dafoster.net
License: MIT
Platform: UNKNOWN
Classifier: Development Status :: 5 - Production/Stable
Classifier: Environment :: Web Environment
Classifier: Intended Audience :: Developers
Classifier: License :: OSI Approved :: MIT License
Classifier: Operating System :: OS Independent
Classifier: Programming Language :: Python
Classifier: Programming Language :: Python :: 3.4
Classifier: Topic :: Database
Classifier: Topic :: Internet :: Proxy Servers
Classifier: Topic :: Internet :: WWW/HTTP
Classifier: Topic :: Internet :: WWW/HTTP :: HTTP Servers
Classifier: Topic :: System :: Archiving
Classifier: Topic :: System :: Archiving :: Backup
Classifier: Topic :: System :: Archiving :: Mirroring
Requires-Dist: certifi
Requires-Dist: ndg-httpsclient
Requires-Dist: pyasn1
Requires-Dist: pyopenssl
Requires-Dist: urllib3 (>=1.15.1)
